jugopy/__init__.py
jugopy/jugopy.py
jugopy-1.0.9.dist-info/METADATA
jugopy-1.0.9.dist-info/WHEEL
jugopy-1.0.9.dist-info/top_level.txt
jugopy-1.0.9.dist-info/RECORD
