Metadata-Version: 2.1
Name: jugopy
Version: 1.0.9
Summary: Mini-framework WSGI en Python avec logs enrichis et design amélioré
Author: Jean Junior LOGBO
Author-email: jeanjuniorlogbo94@gmail.com
Classifier: Development Status :: 4 - Beta
Classifier: Intended Audience :: Developers
Classifier: License :: OSI Approved :: MIT License
Classifier: Operating System :: OS Independent
Classifier: Programming Language :: Python :: 3
Classifier: Programming Language :: Python :: 3.7
Classifier: Programming Language :: Python :: 3.8
Classifier: Programming Language :: Python :: 3.9
Classifier: Programming Language :: Python :: 3.10
Classifier: Programming Language :: Python :: 3.11
Requires-Python: >=3.7
Requires-Dist: Jinja2 (>=3.0.0)
Requires-Dist: PyMySQL (>=1.0.0)
